{
  "project_info": {
    "project_number": "90243313256",
    "project_id": "airplane-d67e6",
    "storage_bucket": "airplane-d67e6.appspot.com"
  },
  "client": [
    {
      "client_info": {
        "mobilesdk_app_id": "1:90243313256:android:ac7250ebd1e44dff2495dd",
        "android_client_info": {
          "package_name": "com.fadly.airplane"
        }
      },
      "oauth_client": [
        {
          "client_id": "90243313256-kkrsft6377el0ep1m5qv5fas3ginivur.apps.googleusercontent.com",
          "client_type": 3
        }
      ],
      "api_key": [
        {
          "current_key": "AIzaSyDOGrEs6AbDwZMD1LAh5m738Z5beDHJ4ck"
        }
      ],
      "services": {
        "appinvite_service": {
          "other_platform_oauth_client": [
            {
              "client_id": "90243313256-kkrsft6377el0ep1m5qv5fas3ginivur.apps.googleusercontent.com",
              "client_type": 3
            }
          ]
        }
      }
    }
  ],
  "configuration_version": "1"
}